dpatk/__init__.py
dpatk/examples.py
dpatk/io.py
dpatk/models.py
dpatk/registration.py
dpatk/utils.py
dpatk-0.0.5.dist-info/METADATA
dpatk-0.0.5.dist-info/WHEEL
dpatk-0.0.5.dist-info/top_level.txt
dpatk-0.0.5.dist-info/RECORD
